auxon_sdk-2.2.0.dist-info/METADATA
auxon_sdk-2.2.0.dist-info/WHEEL
auxon_sdk-2.2.0.dist-info/licenses/LICENSE
auxon_sdk/client.py
auxon_sdk/__init__.py
auxon_sdk/.gitignore
auxon_sdk/go.py
auxon_sdk/attr.py
auxon_sdk/_auxon_sdk.abi3.so
auxon_sdk-2.2.0.dist-info/RECORD
