Metadata-Version: 2.3
Name: auxon-sdk
Version: 2.2.0
Classifier: Programming Language :: Rust
Classifier: Programming Language :: Python :: Implementation :: CPython
Classifier: Programming Language :: Python :: Implementation :: PyPy
Requires-Dist: appdirs
Requires-Dist: pandas
Requires-Dist: toml
License-File: LICENSE
Requires-Python: >=3.8
